launchR/__init__.py
launchR-0.3.0.dist-info/DESCRIPTION.rst
launchR-0.3.0.dist-info/METADATA
launchR-0.3.0.dist-info/RECORD
launchR-0.3.0.dist-info/WHEEL
launchR-0.3.0.dist-info/metadata.json
launchR-0.3.0.dist-info/top_level.txt
