Metadata-Version: 2.0
Name: launchR
Version: 0.3.0
Summary: launchR finds your R installation and provides convenience functions for running R scripts from Python, including package installation and running scripts.
Home-page: https://github.com/ucd-cws/launchR
Author: nickrsan
Author-email: nrsantos@ucdavis.edu
License: UNKNOWN
Platform: UNKNOWN
